README.md
setup.cfg
setup.py
patenteschile/__init__.py
patenteschile/main.py
patenteschile.egg-info/PKG-INFO
patenteschile.egg-info/SOURCES.txt
patenteschile.egg-info/dependency_links.txt
patenteschile.egg-info/top_level.txt