Metadata-Version: 2.1
Name: patenteschile
Version: 0.1
Summary: A small library for generate chilean car registration number
Home-page: https://github.com/fariascl/patentechile
Author: Alejandro Farías
Author-email: farias@8loop.cl
License: UNKNOWN
Platform: UNKNOWN
Classifier: Programming Language :: Python :: 3
Classifier: License :: OSI Approved :: MIT License
Classifier: Operating System :: OS Independent
Requires-Python: >=3.6
